carbonate_sdk/__init__.py
carbonate_sdk/action.py
carbonate_sdk/api.py
carbonate_sdk/browser.py
carbonate_sdk/exceptions.py
carbonate_sdk/logger.py
carbonate_sdk/resources/__init__.py
carbonate_sdk/resources/carbonate.js
carbonate_sdk/sdk.py
carbonate_sdk/slugify.py
carbonate_sdk/test_decorator.py
carbonate_sdk/test_logger.py
carbonate_sdk/webdriver.py
carbonate_sdk-0.1.0.dist-info/LICENSE
carbonate_sdk-0.1.0.dist-info/METADATA
carbonate_sdk-0.1.0.dist-info/WHEEL
carbonate_sdk-0.1.0.dist-info/RECORD
