Metadata-Version: 2.1
Name: carbonate-sdk
Version: 0.1.0
Summary: Run UI tests using AI
License: MIT
Author: Carbonate
Author-email: team@cabonate.dev
Requires-Python: >=3.8.14,<4.0.0
Classifier: License :: OSI Approved :: MIT License
Classifier: Programming Language :: Python :: 3
Classifier: Programming Language :: Python :: 3.9
Classifier: Programming Language :: Python :: 3.10
Classifier: Programming Language :: Python :: 3.11
Requires-Dist: importlib_resources (>=5.12.0,<6.0.0) ; python_version < "3.9"
Requires-Dist: requests (>=2.28.2,<3.0.0)
